 {
"dinner":[
  
   {
    "id": 1,
    "img": "https://i.ibb.co/N25ZJ1K/dinner6.png",
    "title": "Salmon with Grapefruit and Lentil Salad",
    "cost": 9.99,
    "description": "How we dream about our future",
    "rating": 4.5
  },
  {
    "id": 2,
    "img": "https://i.ibb.co/027m3qH/dinner2.png",
    "title": "Lemony Salmon Piccata",
    "cost": 10.99,
    "description": "How we dream about our future.",
    "rating": 4
  },
  {
    "id": 3,
    "img": "https://i.ibb.co/MMS10B7/dinner5.png",
    "title": "Pork Tenderloin with Quinoa Pilaf",
    "cost": 12.99,
    "description": "How we dream about our future.",
    "rating": 3.5
  },
  {
    "id": 4,
    "img": "https://i.ibb.co/4Fc0hDK/dinner4.png",
    "title": "French fries with cheese",
    "cost": 8.99,
    "description": "How we dream about our future.",
    "rating": 4.5
  },
  {
    "id": 5,
    "img": "https://i.ibb.co/Vv93LSh/dinner3.png",
    "title": "Garlic Butter Baken Salmon",
    "cost": 6.99,
    "description": "How we dream about our future.",
    "rating": 4
  },
  {
    "id": 6,
    "img": "https://i.ibb.co/Htct5Y1/dinner1.png",
    "title": "Baked Chiken",
    "cost": 9.99,
    "description": "How we dream about our future.",
    "rating": 4.5
  }
  
],
  "breakfast":
   [
  {
    "id": 1,
    "img": "https://i.ibb.co/XZmGssk/breakfast4.png",
    "title": "Begel and cream cheese",
    "cost": 6.99,
    "description": "How we dream about our future",
    "rating": 4.5
  },
  {
    "id": 2,
    "img": "https://i.ibb.co/k9CTNzb/breakfast2.png",
    "title": "Breakfast sandwich",
    "cost": 9.99,
    "description": "How we dream about our future.",
    "rating": 4
  },
  {
    "id": 3,
    "img": "https://i.ibb.co/kMjtTCL/breakfast3.png",
    "title": "Baked Chiken",
    "cost": 10.99,
    "description": "How we dream about our future.",
    "rating": 3.5
  },
  {
    "id": 4,
    "img": "https://i.ibb.co/gM3msYG/breakfast1.png",
    "title": "Eggs Benedict",
    "cost": 8.99,
    "description": "How we dream about our future.",
    "rating": 4.5
  },
  {
    "id": 5,
    "img": "https://i.ibb.co/nj6LMym/breakfast6.png",
    "title": "Toast Croissant Fried Egg",
    "cost": 19.99,
    "description": "How we dream about our future.",
    "rating": 4
  },
  {
    "id": 6,
    "img": "https://i.ibb.co/Pw97LWB/breakfast5.png",
    "title": "Full Breakfast Fried Egg Toast Brunch",
    "cost": 3.99,
    "description": "How we dream about our future.",
    "rating": 4.5
  }
],
  "lunch":
   [
  {
    "id": 1,
    "img": "https://i.ibb.co/0FyvCKb/lunch6.png",
    "title": "Healthy Meal Plan",
    "cost": 23.99,
    "description": "How we dream about our future",
    "rating": 4.5
  },
  {
    "id": 2,
    "img": "https://i.ibb.co/4N7gvjJ/lunch5.png",
    "title": "Fried Chicken Bento",
    "cost": 9.99,
    "description": "How we dream about our future.",
    "rating": 4
  },
  {
    "id": 3,
    "img": "https://i.ibb.co/SBJJdtJ/lunch3.png",
    "title": "Tarragon-Rubbed-Salmon",
    "cost": 199,
    "description": "How we dream about our future.",
    "rating": 3.5
  },
  {
    "id": 4,
    "img": "https://i.ibb.co/B6BgZ3P/lunch4.png",
    "title": "Indian Lunch",
    "cost": 8.99,
    "description": "How we dream about our future.",
    "rating": 4.5
  },
  {
    "id": 5,
    "img": "https://i.ibb.co/h82r3yZ/lunch1.png",
    "title": "Beef Steak",
    "cost": 15.99,
    "description": "How we dream about our future.",
    "rating": 4
  },
  {
    "id": 6,
    "img": "https://i.ibb.co/vvpYRTr/lunch2.png",
    "title": "Honey-Soy-Glazed Sa;mon with Peppers",
    "cost": 7.99,
    "description": "How we dream about our future.",
    "rating": 4.5
  }
]
}